SilverBotFNPack/__init__.py
SilverBotFNPack-6.9.9.dist-info/LICENSE
SilverBotFNPack-6.9.9.dist-info/METADATA
SilverBotFNPack-6.9.9.dist-info/WHEEL
SilverBotFNPack-6.9.9.dist-info/entry_points.txt
SilverBotFNPack-6.9.9.dist-info/top_level.txt
SilverBotFNPack-6.9.9.dist-info/RECORD
