Metadata-Version: 2.1
Name: SilverBotFNPack
Version: 6.9.9
Summary: Imagine.
Home-page: UNKNOWN
Author: mxnty
Author-email: silverbotbusiness@protonmail.com
License: MIT
Platform: UNKNOWN
Classifier: License :: OSI Approved :: MIT License
Classifier: Programming Language :: Python :: 3
Classifier: Programming Language :: Python :: 3.7
Requires-Dist: requests
